.gitignore
MANIFEST.in
README.md
setup.cfg
setup.py
beancount_future_transactions.egg-info/PKG-INFO
beancount_future_transactions.egg-info/SOURCES.txt
beancount_future_transactions.egg-info/dependency_links.txt
beancount_future_transactions.egg-info/not-zip-safe
beancount_future_transactions.egg-info/top_level.txt
src/beancount_extensions/__init__.py
src/beancount_extensions/future_transactions/__init__.py
src/beancount_extensions/future_transactions/test_transactions.py