Metadata-Version: 2.1
Name: beancount-future-transactions
Version: 0.0.5
Summary: A plugin for Beancount that suppresses future transactions
Home-page: http://github.com/Rudd-O/beancount-future-transactions
Author: Manuel Amador (Rudd-O)
Author-email: rudd-o@rudd-o.com
License: GPL
Classifier: Development Status :: 4 - Beta
Classifier: Environment :: Console
Classifier: Intended Audience :: End Users/Desktop
Classifier: License :: OSI Approved :: GNU General Public License (GPL)
Classifier: Operating System :: POSIX :: Linux
Classifier: Programming Language :: Python :: 3 :: Only
Requires: beancount
